{
"type": "FeatureCollection",
"crs": { "type": "name", "properties": { "name": "urn:ogc:def:crs:OGC:1.3:CRS84" } },
"features": [
{ "type": "Feature", "properties": { "Id": 0, "Name": "377", "Descript": null, "Type": "WPT", "Comment": "خزان ارضى الكاسر", "Symbol": "Flag, Green", "DateTimeS": "2016-12-09T07:08:04Z", "Elevation": 85.01963, "code": 13, "ROOM": null }, "geometry": { "type": "Point", "coordinates": [ 32.438877, 29.924115, 85.019630000000006 ] } },
{ "type": "Feature", "properties": { "Id": 0, "Name": "388", "Descript": null, "Type": "WPT", "Comment": "خزان التكديس", "Symbol": "Flag, Green", "DateTimeS": "2016-12-09T07:52:34Z", "Elevation": 108.384415, "code": 13, "ROOM": null }, "geometry": { "type": "Point", "coordinates": [ 32.435040000000001, 29.928547, 108.384415 ] } },
{ "type": "Feature", "properties": { "Id": 0, "Name": "006", "Descript": null, "Type": "WPT", "Comment": "نقطه داخل المحطه", "Symbol": "Flag, Green", "DateTimeS": "2016-11-21T09:57:29Z", "Elevation": 248.931107, "code": 13, "ROOM": "نقطه داخل المحطه" }, "geometry": { "type": "Point", "coordinates": [ 32.057371000000003, 30.071774000000001, 248.931107 ] } },
{ "type": "Feature", "properties": { "Id": 0, "Name": "019", "Descript": null, "Type": "WPT", "Comment": "خزان القمه خزانين", "Symbol": "Flag, Green", "DateTimeS": "2016-11-21T11:55:31Z", "Elevation": 330.085083, "code": 13, "ROOM": "خزان القمة" }, "geometry": { "type": "Point", "coordinates": [ 32.140534000000002, 29.967775, 330.085083 ] } },
{ "type": "Feature", "properties": { "Id": 0, "Name": "023", "Descript": null, "Type": "WPT", "Comment": "خزان كسر ا", "Symbol": "Flag, Green", "DateTimeS": "2016-11-21T12:12:32Z", "Elevation": 246.570511, "code": 13, "ROOM": "خزان كاسر 1" }, "geometry": { "type": "Point", "coordinates": [ 32.193743, 29.924533, 246.57051100000001 ] } },
{ "type": "Feature", "properties": { "Id": 0, "Name": "027", "Descript": null, "Type": "WPT", "Comment": "بين الخزانين", "Symbol": "Flag, Green", "DateTimeS": "2016-11-21T12:18:25Z", "Elevation": 247.352188, "code": 13, "ROOM": "نقطه بين التنكين" }, "geometry": { "type": "Point", "coordinates": [ 32.193508000000001, 29.924253, 247.35218800000001 ] } },
{ "type": "Feature", "properties": { "Id": 0, "Name": "034", "Descript": null, "Type": "WPT", "Comment": "كسر2", "Symbol": "Flag, Green", "DateTimeS": "2016-11-21T12:45:03Z", "Elevation": 159.522446, "code": 13, "ROOM": "خزان كاسر 2" }, "geometry": { "type": "Point", "coordinates": [ 32.262721, 29.856435000000001, 159.522446 ] } },
{ "type": "Feature", "properties": { "Id": 0, "Name": "058", "Descript": null, "Type": "WPT", "Comment": "محطه التك\nمحطه التكديس", "Symbol": "Flag, Green", "DateTimeS": "2016-11-21T13:51:38Z", "Elevation": 83.90641, "code": 13, "ROOM": "خزان التكديس" }, "geometry": { "type": "Point", "coordinates": [ 32.248648000000003, 29.740101, 83.90641 ] } },
{ "type": "Feature", "properties": { "Id": 0, "Name": "152", "Descript": null, "Type": "WPT", "Comment": "خذان داخل ألمحطة", "Symbol": "Flag, Green", "DateTimeS": "2016-11-22T16:59:54Z", "Elevation": 35.688354, "code": 13, "ROOM": "خزان داخل المحطه" }, "geometry": { "type": "Point", "coordinates": [ 32.314808, 29.593387, 35.688354 ] } }
]
}
